aaryan/__init__.py
aaryan/__main__.py
topsis_aaryan_102003541-1.0.0.dist-info/LICENSE
topsis_aaryan_102003541-1.0.0.dist-info/METADATA
topsis_aaryan_102003541-1.0.0.dist-info/WHEEL
topsis_aaryan_102003541-1.0.0.dist-info/entry_points.txt
topsis_aaryan_102003541-1.0.0.dist-info/top_level.txt
topsis_aaryan_102003541-1.0.0.dist-info/RECORD
