Metadata-Version: 2.1
Name: topsis-aaryan-102003541
Version: 1.0.0
Summary: topsis implementation
Home-page: UNKNOWN
Author: Aaryan Jain
Author-email: jainaaryan2001@gmail.com
License: UNKNOWN
Platform: UNKNOWN
Classifier: Programming Language :: Python :: 3
Classifier: License :: OSI Approved :: MIT License
Classifier: Operating System :: OS Independent
Requires-Python: >=3.6
License-File: LICENSE
